xrayutilities-1.7.12.dist-info/RECORD
xrayutilities-1.7.12.dist-info/WHEEL
xrayutilities-1.7.12.dist-info/METADATA
xrayutilities-1.7.12.dist-info/licenses/LICENSE.txt
xrayutilities/gridder.py
xrayutilities/exception.py
xrayutilities/xrayutilities_default.conf
xrayutilities/config.py
xrayutilities/normalize.py
xrayutilities/q2ang_fit.py
xrayutilities/utilities_noconf.py
xrayutilities/__init__.py
xrayutilities/cxrayutilities.cpython-311-darwin.so
xrayutilities/experiment.py
xrayutilities/gridder2d.py
xrayutilities/gridder3d.py
xrayutilities/utilities.py
xrayutilities/mpl_helper.py
xrayutilities/materials/heuslerlib.py
xrayutilities/materials/_create_database.py
xrayutilities/materials/material.py
xrayutilities/materials/plot.py
xrayutilities/materials/predefined_materials.py
xrayutilities/materials/spacegrouplattice.py
xrayutilities/materials/elements.py
xrayutilities/materials/database.py
xrayutilities/materials/__init__.py
xrayutilities/materials/wyckpos.py
xrayutilities/materials/cif.py
xrayutilities/materials/atom.py
xrayutilities/materials/__pycache__/database.cpython-310.pyc
xrayutilities/materials/__pycache__/database.cpython-311.pyc
xrayutilities/materials/data/colors.dat
xrayutilities/materials/data/f1f2_Henke.dat.xz
xrayutilities/materials/data/f0_xop.dat.xz
xrayutilities/materials/data/f1f2_asf_Kissel.dat.xz
xrayutilities/materials/data/f0_InterTables.dat.xz
xrayutilities/materials/data/atomic_radius.dat
xrayutilities/materials/data/nist_atom.dat
xrayutilities/materials/data/README.txt
xrayutilities/materials/data/elements.db
xrayutilities/analysis/line_cuts.py
xrayutilities/analysis/misc.py
xrayutilities/analysis/sample_align.py
xrayutilities/analysis/__init__.py
xrayutilities/simpack/powder.py
xrayutilities/simpack/fit.py
xrayutilities/simpack/models.py
xrayutilities/simpack/powdermodel.py
xrayutilities/simpack/__init__.py
xrayutilities/simpack/mosaicity.py
xrayutilities/simpack/smaterials.py
xrayutilities/simpack/darwin_theory.py
xrayutilities/simpack/helpers.py
xrayutilities/io/cbf.py
xrayutilities/io/pdcif.py
xrayutilities/io/edf.py
xrayutilities/io/__init__.py
