Metadata-Version: 2.4
Name: xrayutilities
Version: 1.7.12
Summary: Package for x-ray diffraction data evaluation
Keywords: x-ray,diffraction,data analysis
Author-Email: Dominik Kriegner <dominik.kriegner@gmail.com>, Eugen Wintersberger <eugen.wintersberger@desy.de>
Maintainer-Email: Dominik Kriegner <dominik.kriegner@gmail.com>
License-Expression: GPL-2.0-or-later
License-File: LICENSE.txt
Classifier: Programming Language :: C
Classifier: Programming Language :: Python :: 3.10
Classifier: Programming Language :: Python :: 3.11
Classifier: Programming Language :: Python :: 3.12
Classifier: Programming Language :: Python :: 3.13
Classifier: Programming Language :: Python :: 3.14
Classifier: Topic :: Scientific/Engineering :: Physics
Classifier: Intended Audience :: Science/Research
Classifier: Development Status :: 5 - Production/Stable
Project-URL: homepage, https://xrayutilities.sourceforge.io
Project-URL: source, https://github.com/dkriegner/xrayutilities
Project-URL: download, https://pypi.org/project/xrayutilities/#files
Project-URL: tracker, https://github.com/dkriegner/xrayutilities/issues
Requires-Python: <4.0,>=3.7
Requires-Dist: numpy>=1.9.2
Requires-Dist: scipy>=0.18.0
Requires-Dist: h5py
Requires-Dist: lmfit>=1.0.1
Provides-Extra: plot
Requires-Dist: matplotlib>=3.1.0; extra == "plot"
Provides-Extra: 3d
Requires-Dist: mayavi; extra == "3d"
Provides-Extra: dev
Requires-Dist: pytest; extra == "dev"
Requires-Dist: pytest-subtests; extra == "dev"
Requires-Dist: pytest-cov; extra == "dev"
Requires-Dist: coverage[toml]; extra == "dev"
Requires-Dist: pytest-azurepipelines; extra == "dev"
Requires-Dist: ruff; extra == "dev"
